unopt/__init__.py
unopt/_version.py
unopt/core.py
unopt/py.typed
unopt-0.2.0.dist-info/METADATA
unopt-0.2.0.dist-info/WHEEL
unopt-0.2.0.dist-info/licenses/LICENSE
unopt-0.2.0.dist-info/RECORD
