Metadata-Version: 2.1
Name: unopt
Version: 0.2.0
Summary: Utility functions to unwrap Optional values
Project-URL: Homepage, https://github.com/odashi/unopt-py
Project-URL: Bug Tracker, https://github.com/odashi/unopt-py/issues
Author-email: Yusuke Oda <odashi@predicate.jp>
License: Apache Software License 2.0
License-File: LICENSE
Keywords: none,optional,rust
Classifier: License :: OSI Approved :: MIT License
Classifier: Operating System :: OS Independent
Classifier: Programming Language :: Python :: 3
Classifier: Programming Language :: Python :: 3.8
Classifier: Programming Language :: Python :: 3.9
Classifier: Programming Language :: Python :: 3.10
Classifier: Programming Language :: Python :: 3.11
Classifier: Programming Language :: Python :: 3.12
Requires-Python: <=3.13,>=3.8
Provides-Extra: dev
Requires-Dist: black>=23.10.1; extra == 'dev'
Requires-Dist: build>=0.8; extra == 'dev'
Requires-Dist: flake8>=6.1.0; extra == 'dev'
Requires-Dist: isort>=5.12.0; extra == 'dev'
Requires-Dist: mypy>=1.6.1; extra == 'dev'
Requires-Dist: pyproject-flake8>=6.1.0; extra == 'dev'
Requires-Dist: pytest>=7.4.3; extra == 'dev'
Provides-Extra: mypy
Requires-Dist: mypy>=1.6.1; extra == 'mypy'
Requires-Dist: pytest>=7.4.3; extra == 'mypy'
